odoo/addons/base_m2m_custom_field/README.rst
odoo/addons/base_m2m_custom_field/__init__.py
odoo/addons/base_m2m_custom_field/__manifest__.py
odoo/addons/base_m2m_custom_field/fields.py
odoo/addons/base_m2m_custom_field/i18n/base_m2m_custom_field.pot
odoo/addons/base_m2m_custom_field/i18n/it.po
odoo/addons/base_m2m_custom_field/readme/CONTRIBUTORS.md
odoo/addons/base_m2m_custom_field/readme/DESCRIPTION.md
odoo/addons/base_m2m_custom_field/readme/USAGE.md
odoo/addons/base_m2m_custom_field/static/description/icon.png
odoo/addons/base_m2m_custom_field/static/description/index.html
odoo_addon_base_m2m_custom_field-18.0.1.0.0.3.dist-info/METADATA
odoo_addon_base_m2m_custom_field-18.0.1.0.0.3.dist-info/WHEEL
odoo_addon_base_m2m_custom_field-18.0.1.0.0.3.dist-info/top_level.txt
odoo_addon_base_m2m_custom_field-18.0.1.0.0.3.dist-info/RECORD
